lava/frameworks/loihi2.py
lava/magma/compiler/LICENSE
lava/magma/compiler/builders/channel_builder.py
lava/magma/compiler/builders/interfaces.py
lava/magma/compiler/builders/py_builder.py
lava/magma/compiler/builders/runtimeservice_builder.py
lava/magma/compiler/channel_map.py
lava/magma/compiler/channels/interfaces.py
lava/magma/compiler/channels/pypychannel.py
lava/magma/compiler/channels/watchdog.py
lava/magma/compiler/compiler.py
lava/magma/compiler/compiler_graphs.py
lava/magma/compiler/compiler_utils.py
lava/magma/compiler/exceptions.py
lava/magma/compiler/executable.py
lava/magma/compiler/mappable_interface.py
lava/magma/compiler/mapper.py
lava/magma/compiler/node.py
lava/magma/compiler/subcompilers/address.py
lava/magma/compiler/subcompilers/channel_builders_factory.py
lava/magma/compiler/subcompilers/channel_map_updater.py
lava/magma/compiler/subcompilers/constants.py
lava/magma/compiler/subcompilers/exceptions.py
lava/magma/compiler/subcompilers/interfaces.py
lava/magma/compiler/subcompilers/py/pyproc_compiler.py
lava/magma/compiler/utils.py
lava/magma/compiler/var_model.py
lava/magma/core/LICENSE
lava/magma/core/callback_fx.py
lava/magma/core/decorator.py
lava/magma/core/learning/constants.py
lava/magma/core/learning/learning_rule.py
lava/magma/core/learning/learning_rule_applier.py
lava/magma/core/learning/product_series.py
lava/magma/core/learning/random.py
lava/magma/core/learning/string_symbols.py
lava/magma/core/learning/symbolic_equation.py
lava/magma/core/learning/utils.py
lava/magma/core/model/interfaces.py
lava/magma/core/model/model.py
lava/magma/core/model/py/connection.py
lava/magma/core/model/py/model.py
lava/magma/core/model/py/neuron.py
lava/magma/core/model/py/ports.py
lava/magma/core/model/py/type.py
lava/magma/core/model/spike_type.py
lava/magma/core/model/sub/model.py
lava/magma/core/process/connection.py
lava/magma/core/process/interfaces.py
lava/magma/core/process/message_interface_enum.py
lava/magma/core/process/neuron.py
lava_nc-0.10.0.dist-info/LICENSE
lava_nc-0.10.0.dist-info/METADATA
lava_nc-0.10.0.dist-info/WHEEL
lava_nc-0.10.0.dist-info/RECORD
